kivy_garden/radialslider/__init__.py
kivy_garden/radialslider/_version.py
kivy_garden/radialslider/tests/test_import.py
kivy_garden.radialslider-0.1.2.dist-info/AUTHORS.txt
kivy_garden.radialslider-0.1.2.dist-info/LICENSE.txt
kivy_garden.radialslider-0.1.2.dist-info/METADATA
kivy_garden.radialslider-0.1.2.dist-info/WHEEL
kivy_garden.radialslider-0.1.2.dist-info/top_level.txt
kivy_garden.radialslider-0.1.2.dist-info/RECORD
