Metadata-Version: 2.1
Name: kivy-garden.radialslider
Version: 0.1.2
Summary: A kivy garden radialslider.
Home-page: https://github.com/kivy-garden/radialslider
Author: Kivy
Author-email: kivy@kivy.org
License: UNKNOWN
Project-URL: Bug Reports, https://github.com/kivy-garden/radialslider/issues
Project-URL: Source, https://github.com/kivy-garden/radialslider
Keywords: Kivy kivy-garden
Platform: UNKNOWN
Classifier: Development Status :: 4 - Beta
Classifier: Intended Audience :: Developers
Classifier: Topic :: Software Development :: Libraries
Classifier: License :: OSI Approved :: MIT License
Classifier: Programming Language :: Python :: 3.5
Classifier: Programming Language :: Python :: 3.6
Classifier: Programming Language :: Python :: 3.7
Classifier: Programming Language :: Python :: 3.8
Provides-Extra: ci
Requires-Dist: coveralls ; extra == 'ci'
Requires-Dist: pycodestyle ; extra == 'ci'
Provides-Extra: dev
Requires-Dist: pytest (>=3.6) ; extra == 'dev'
Requires-Dist: pytest-cov ; extra == 'dev'
Requires-Dist: pytest-asyncio ; extra == 'dev'
Requires-Dist: sphinx-rtd-theme ; extra == 'dev'
